cookiepatcher/__init__.py
cookiepatcher/__main__.py
cookiepatcher/cli.py
cookiepatcher-0.5.0.dist-info/AUTHORS.rst
cookiepatcher-0.5.0.dist-info/LICENSE
cookiepatcher-0.5.0.dist-info/METADATA
cookiepatcher-0.5.0.dist-info/WHEEL
cookiepatcher-0.5.0.dist-info/entry_points.txt
cookiepatcher-0.5.0.dist-info/top_level.txt
cookiepatcher-0.5.0.dist-info/RECORD
