Metadata-Version: 2.1
Name: cookiepatcher
Version: 0.5.0
Summary: Just a small shim around cookiecutter that alters a bit the CLI to work better when reapplying templates to existing projects. Works best with cookiecutter-pylibrary.
Home-page: https://github.com/ionelmc/python-cookiepatcher
Author: Ionel Cristian Mărieș
Author-email: contact@ionelmc.ro
License: BSD-2-Clause
Project-URL: Changelog, https://github.com/ionelmc/python-cookiepatcher/blob/master/CHANGELOG.rst
Project-URL: Issue Tracker, https://github.com/ionelmc/python-cookiepatcher/issues
Platform: UNKNOWN
Classifier: Development Status :: 5 - Production/Stable
Classifier: Intended Audience :: Developers
Classifier: License :: OSI Approved :: BSD License
Classifier: Operating System :: Unix
Classifier: Operating System :: POSIX
Classifier: Operating System :: Microsoft :: Windows
Classifier: Programming Language :: Python
Classifier: Programming Language :: Python :: 3
Classifier: Programming Language :: Python :: 3 :: Only
Classifier: Programming Language :: Python :: 3.7
Classifier: Programming Language :: Python :: 3.8
Classifier: Programming Language :: Python :: 3.9
Classifier: Programming Language :: Python :: 3.10
Classifier: Programming Language :: Python :: Implementation :: CPython
Classifier: Programming Language :: Python :: Implementation :: PyPy
Classifier: Topic :: Utilities
Requires-Python: >=3.7
License-File: LICENSE
License-File: AUTHORS.rst
Requires-Dist: click
Requires-Dist: cookiecutter (>=1.7)
Requires-Dist: aspectlib
Requires-Dist: pyyaml (>=6.0)
